README.md
setup.py
megastep/__init__.py
megastep/core.py
megastep/cubicasa.py
megastep/geometry.py
megastep/modules.py
megastep/plotting.py
megastep/ragged.py
megastep/scene.py
megastep/spaces.py
megastep/toys.py
megastep.egg-info/PKG-INFO
megastep.egg-info/SOURCES.txt
megastep.egg-info/dependency_links.txt
megastep.egg-info/requires.txt
megastep.egg-info/top_level.txt
megastep/demo/__init__.py
megastep/demo/heads.py
megastep/demo/learning.py
megastep/demo/lstm.py
megastep/demo/transformer.py
megastep/demo/envs/__init__.py
megastep/demo/envs/deathmatch.py
megastep/demo/envs/explorer.py
megastep/demo/envs/minimal.py
megastep/src/common.h
megastep/src/kernels.cu
megastep/src/wrappers.cpp
rebar/__init__.py
rebar/arrdict.py
rebar/contextlib.py
rebar/dotdict.py
rebar/fsm.py
rebar/interrupting.py
rebar/logging.py
rebar/numpy.py
rebar/parallel.py
rebar/paths.py
rebar/plots.py
rebar/processes.py
rebar/queuing.py
rebar/recording.py
rebar/recurrence.py
rebar/storing.py
rebar/widgets.py
rebar/stats/__init__.py
rebar/stats/categories.py
rebar/stats/gpu.py
rebar/stats/reading.py
rebar/stats/writing.py