Metadata-Version: 2.1
Name: megastep
Version: 0.2.4
Summary: Helps build million-frame-per-second reinforcement learning environments
Home-page: http://andyljones.com/megastep
Author: Andy Jones
Author-email: andyjones.ed@gmail.com
License: UNKNOWN
Platform: UNKNOWN
Requires-Python: >=3.6
Provides-Extra: cubicasa
Provides-Extra: rebar
Provides-Extra: docs
Provides-Extra: test
